checkerboard/__init__.py
checkerboard/checkerboard.py
checkerboard-0.2.4.dist-info/LICENSE
checkerboard-0.2.4.dist-info/METADATA
checkerboard-0.2.4.dist-info/WHEEL
checkerboard-0.2.4.dist-info/top_level.txt
checkerboard-0.2.4.dist-info/RECORD
