Metadata-Version: 2.1
Name: checkerboard
Version: 0.2.4
Summary: More robust checkerboard detection, similar algorithm to libcbdetect
Home-page: https://github.com/lambdaloop/checkerboard
Author: Pierre Karashchuk
Author-email: krchtchk@gmail.com
License: UNKNOWN
Platform: UNKNOWN
Classifier: Programming Language :: Python :: 3
Classifier: License :: OSI Approved :: BSD License
Classifier: Intended Audience :: Science/Research
Classifier: Topic :: Scientific/Engineering
Classifier: Topic :: Scientific/Engineering :: Image Recognition
Requires-Dist: opencv-python
Provides-Extra: gpu
Requires-Dist: gputools ; extra == 'gpu'
